targetran/__init__.py
targetran/_check.py
targetran/_np_functional.py
targetran/_tf_functional.py
targetran/_transform.py
targetran/_typing.py
targetran/py.typed
targetran/np/__init__.py
targetran/np/_np.py
targetran/tf/__init__.py
targetran/tf/_tf.py
targetran/utils/__init__.py
targetran/utils/_utils.py
tests/__init__.py
tests/_test.py
tests/run_pt_dataset_test.py
tests/run_tf_dataset_test.py
tests/run_tf_dataset_timing.py
targetran-0.13.2.dist-info/LICENSE
targetran-0.13.2.dist-info/METADATA
targetran-0.13.2.dist-info/WHEEL
targetran-0.13.2.dist-info/top_level.txt
targetran-0.13.2.dist-info/RECORD
