Metadata-Version: 2.2
Name: targetran
Version: 0.13.2
Summary: Target transformation for data augmentation in objection detection
Home-page: https://github.com/bhky/targetran
Author: attr: targetran.__author__
Author-email: bhky.dev@gmail.com
Classifier: Programming Language :: Python :: 3
Classifier: License :: OSI Approved :: MIT License
Classifier: Operating System :: OS Independent
Requires-Python: >=3.8
License-File: LICENSE
Requires-Dist: opencv-python
Requires-Dist: numpy>=1.22.0
